cubitpy/__init__.py
cubitpy/conf.py
cubitpy/cubit_group.py
cubitpy/cubit_to_fourc_input.py
cubitpy/cubit_utility.py
cubitpy/cubitpy.py
cubitpy/cubitpy_types.py
cubitpy/geometry_creation_functions.py
cubitpy/mesh_creation_functions.py
cubitpy/cubit_wrapper/__init__.py
cubitpy/cubit_wrapper/cubit_wrapper_client.py
cubitpy/cubit_wrapper/cubit_wrapper_host.py
cubitpy/cubit_wrapper/cubit_wrapper_utility.py
cubitpy-0.1.1.dist-info/licenses/LICENSE
tutorial/__init__.py
tutorial/tutorial.py
cubitpy-0.1.1.dist-info/METADATA
cubitpy-0.1.1.dist-info/WHEEL
cubitpy-0.1.1.dist-info/top_level.txt
cubitpy-0.1.1.dist-info/RECORD
