Metadata-Version: 2.4
Name: cubitpy
Version: 0.1.1
Summary: CubitPy: Utility functions and 4C related functionality for the Cubit and Coreform python interface
Author-email: Ivo Steinbrecher <ivo.steinbrecher@unibw.de>
License-Expression: MIT
Project-URL: Repository, https://github.com/imcs-compsim/cubitpy/
Project-URL: Issues, https://github.com/imcs-compsim/cubitpy/issues/
License-File: LICENSE
Requires-Dist: execnet==1.9.0
Requires-Dist: netCDF4
Requires-Dist: numpy
Requires-Dist: fourcipp
Provides-Extra: dev
Requires-Dist: pre-commit; extra == "dev"
Requires-Dist: pytest; extra == "dev"
Requires-Dist: pytest-cov; extra == "dev"
Requires-Dist: deepdiff; extra == "dev"
Dynamic: license-file
